Metadata-Version: 2.3
Name: cozepy-flink
Version: 0.13.1.post2
Summary: OpenAPI SDK for Coze(coze.com/coze.cn) - Custom Version
License: MIT
Author: chyroc
Author-email: chyroc@bytedance.com
Requires-Python: >=3.9,<4.0
Classifier: License :: OSI Approved :: MIT License
Classifier: Programming Language :: Python :: 3
Classifier: Programming Language :: Python :: 3.9
Classifier: Programming Language :: Python :: 3.10
Classifier: Programming Language :: Python :: 3.11
Classifier: Programming Language :: Python :: 3.12
Classifier: Programming Language :: Python :: 3.13
Requires-Dist: authlib (>=1.2.0,<2.0.0)
Requires-Dist: distro (>=1.9.0,<2.0.0)
Requires-Dist: httpx (>=0.27.0,<0.28.0)
Requires-Dist: pydantic (>=2.5.0,<3.0.0)
Requires-Dist: typing-extensions (>=4.3.0,<5.0.0)
Requires-Dist: websockets (>=14.1.0,<15.0.0)
